{
  "version": 1,
  "requestId": null,
  "time": "2019-11-21 09:45:15",
  "code": 200,
  "success": true,
  "message": "公告通知",
  "data": [
    {
      "类型": "邀约削峰",
      "年度启动次数":2,
      "年度参与次数": 2,
      "响应成功率": "90%",
      "累计响应负荷": 1030,
      "累计补偿金额": 542
    },
    {
      "类型": "邀约填谷",
      "年度启动次数":2,
      "年度参与次数": 2,
      "响应成功率": "80%",
      "累计响应负荷": 1310,
      "累计补偿金额": 364
    },
    {
      "类型": "实时削峰",
      "年度启动次数":2,
      "年度参与次数": 2,
      "响应成功率": "70%",
      "累计响应负荷": 900,
      "累计补偿金额": 789
    },
    {
      "类型": "实时填谷",
      "年度启动次数":2,
      "年度参与次数": 2,
      "响应成功率": "85%",
      "累计响应负荷": 1030,
      "累计补偿金额": 352
    },
    {
      "类型": "合计",
      "年度启动次数":8,
      "年度参与次数": 8,
      "响应成功率": "90%",
      "累计响应负荷": 5000,
      "累计补偿金额": 542
    }
  ],
  "dataExt": null
}